cdktf_simple_l2_bucket/__init__.py
cdktf_simple_l2_bucket/py.typed
cdktf_simple_l2_bucket/_jsii/__init__.py
cdktf_simple_l2_bucket/_jsii/workshop-code@0.0.0.jsii.tgz
cdktf_simple_l2_bucket-0.0.0.dist-info/LICENSE
cdktf_simple_l2_bucket-0.0.0.dist-info/METADATA
cdktf_simple_l2_bucket-0.0.0.dist-info/WHEEL
cdktf_simple_l2_bucket-0.0.0.dist-info/top_level.txt
cdktf_simple_l2_bucket-0.0.0.dist-info/RECORD
