Metadata-Version: 2.1
Name: cdktf-simple-l2-bucket
Version: 0.0.0
Summary: workshop-code
Home-page: https://github.com/rafams/workshop-code.git
Author: Rafael Mosca<rafams@amazon.es>
License: Apache-2.0
Project-URL: Source, https://github.com/rafams/workshop-code.git
Classifier: Intended Audience :: Developers
Classifier: Operating System :: OS Independent
Classifier: Programming Language :: JavaScript
Classifier: Programming Language :: Python :: 3 :: Only
Classifier: Programming Language :: Python :: 3.7
Classifier: Programming Language :: Python :: 3.8
Classifier: Programming Language :: Python :: 3.9
Classifier: Programming Language :: Python :: 3.10
Classifier: Typing :: Typed
Classifier: Development Status :: 5 - Production/Stable
Classifier: License :: OSI Approved
Requires-Python: ~=3.7
License-File: LICENSE
Requires-Dist: cdktf-cdktf-provider-aws (<11.0.0,>=10.0.11)
Requires-Dist: cdktf (<0.14.0,>=0.13.3)
Requires-Dist: constructs (<11.0.0,>=10.1.159)
Requires-Dist: jsii (<2.0.0,>=1.71.0)
Requires-Dist: publication (>=0.0.3)
Requires-Dist: typeguard (~=2.13.3)
